MANIFEST.in
README.md
setup.cfg
setup.py
bin/csrec_webapp.py
cold_start_recommender_webapp.egg-info/PKG-INFO
cold_start_recommender_webapp.egg-info/SOURCES.txt
cold_start_recommender_webapp.egg-info/dependency_links.txt
cold_start_recommender_webapp.egg-info/requires.txt
cold_start_recommender_webapp.egg-info/top_level.txt
csrec_webapp/__init__.py