Metadata-Version: 1.1
Name: cold-start-recommender-webapp
Version: 0.4.1
Summary: Webapp for the cold start recommender
Home-page: https://github.com/elegans-io/csrec-webapp
Author: elegans.io Ltd
Author-email: info@elegans.io
License: GPL v2
Keywords: recommendations,recommender,recommendation engine
Platform: UNKNOWN
Classifier: Development Status :: 4 - Beta
Classifier: Intended Audience :: Information Technology
Classifier: Topic :: Scientific/Engineering :: Artificial Intelligence
Classifier: License :: OSI Approved :: GNU General Public License v2 (GPLv2)
Classifier: Programming Language :: Python :: 2.7
